getpodcast.py
getpodcast-1.0.11.dist-info/METADATA
getpodcast-1.0.11.dist-info/WHEEL
getpodcast-1.0.11.dist-info/top_level.txt
getpodcast-1.0.11.dist-info/RECORD
