Metadata-Version: 2.1
Name: getpodcast
Version: 1.0.11
Summary: Download podcast
Home-page: https://gitlab.com/fholmer/getpodcast
Author: Frode Holmer
Author-email: fholmer+getpodcast@gmail.com
License: MIT
Project-URL: Source Code, https://gitlab.com/fholmer/getpodcast
Keywords: podcast,client,resume,download
Classifier: Development Status :: 5 - Production/Stable
Classifier: Intended Audience :: End Users/Desktop
Classifier: Topic :: Home Automation
Classifier: License :: OSI Approved :: MIT License
Classifier: Programming Language :: Python :: 3
Requires-Dist: pyPodcastParser
